file_registry/__init__.py
file_registry/file_registry.py
file_registry-0.0.46.dist-info/LICENSE
file_registry-0.0.46.dist-info/METADATA
file_registry-0.0.46.dist-info/WHEEL
file_registry-0.0.46.dist-info/top_level.txt
file_registry-0.0.46.dist-info/RECORD
