Metadata-Version: 2.1
Name: file_registry
Version: 0.0.46
Summary: File management scripts
Home-page: https://github.com/obozkanucla/file_registry
Author: Omer Burak Ozkan
Author-email: oburako@gmail.com
License: UNKNOWN
Project-URL: Bug Tracker, https://github.com/obozkanucla/file_registry/issues
Platform: UNKNOWN
Classifier: Programming Language :: Python :: 3
Classifier: License :: OSI Approved :: MIT License
Classifier: Operating System :: OS Independent
Requires-Python: >=3.6
License-File: LICENSE
